kaskada-0.6.1.dist-info/METADATA
kaskada-0.6.1.dist-info/WHEEL
kaskada/destinations.py
kaskada/_ffi.pyi
kaskada/plot.py
kaskada/results.py
kaskada/__init__.py
kaskada/_execution.py
kaskada/_session.py
kaskada/_timestream.py
kaskada/py.typed
kaskada/sources/arrow.py
kaskada/sources/__init__.py
kaskada/sources/source.py
kaskada/windows.py
kaskada/udf.py
kaskada/_ffi.abi3.so
kaskada-0.6.1.dist-info/RECORD
