Metadata-Version: 2.1
Name: kaskada
Version: 0.6.1
Classifier: Development Status :: 3 - Alpha
Requires-Dist: pandas >=2.0.0, <3.0.0
Requires-Dist: pyarrow >=12.0.0
Requires-Dist: typing-extensions >=4.6.0
Requires-Dist: plotly >=5.0.0, <6.0.0 ; extra == 'plot'
Requires-Dist: graphviz >=0.20.1, <1.0.0 ; extra == 'explain'
Provides-Extra: plot
Provides-Extra: explain
Summary: Kaskada query builder and local execution engine.
Author: Kaskada Developers
License: Apache-2.0
Requires-Python: >=3.9, <4.0
